black_junit/__init__.py
black_junit/__pkginfo__.py
black_junit/main.py
black_junit-0.2.5.dist-info/LICENSE
black_junit-0.2.5.dist-info/METADATA
black_junit-0.2.5.dist-info/WHEEL
black_junit-0.2.5.dist-info/entry_points.txt
black_junit-0.2.5.dist-info/top_level.txt
black_junit-0.2.5.dist-info/RECORD
